[
  {
    "id": "70d2b2d5-70dd-46d1-ae66-b64a729afe99",
    "data": [
      {
        "text": "gagal saat mencoba menghubungkan akun tokopedia dengan ",
        "userDefined": false
      },
      {
        "text": "ovo",
        "meta": "@sys.ignore",
        "userDefined": false
      }
    ],
    "isTemplate": false,
    "count": 0
  },
  {
    "id": "22c8b375-73e0-4276-acfa-3c71312159c7",
    "data": [
      {
        "text": "kenapa ga bisa hubungkan akun tokopedia dan ",
        "userDefined": false
      },
      {
        "text": "ovo",
        "meta": "@sys.ignore",
        "userDefined": false
      }
    ],
    "isTemplate": false,
    "count": 0
  },
  {
    "id": "bee207dc-68a5-45c0-9e8c-9f7761808674",
    "data": [
      {
        "text": "tidak bisa gabungkan akun tokopedia dengan ovo",
        "userDefined": false
      }
    ],
    "isTemplate": false,
    "count": 0
  },
  {
    "id": "856c5ff1-cbaa-4ada-8a50-23814eeeba25",
    "data": [
      {
        "text": "saya tidak bisa menghubungkan akun Tokopedia dengan OVO",
        "userDefined": false
      }
    ],
    "isTemplate": false,
    "count": 0
  },
  {
    "id": "cf3ab95f-a1ef-4cff-8c90-9a7ae60c25dd",
    "data": [
      {
        "text": "mengapa tidak bisa gabungkan akun tokopedia dengan ovo",
        "userDefined": false
      }
    ],
    "isTemplate": false,
    "count": 0
  },
  {
    "id": "22545747-5487-45f2-a6bd-d26f466797bf",
    "data": [
      {
        "text": "tokocash saya TDK bs link or ovo.",
        "userDefined": false
      }
    ],
    "isTemplate": false,
    "count": 1
  },
  {
    "id": "d6d453b5-971d-4997-891f-55a72428c92d",
    "data": [
      {
        "text": "halo min, saya mau coba aktivasi ovo lewat tokopedia nih kan pindah dari toko cash ke ovo, tapi muncul error internal error",
        "userDefined": false
      }
    ],
    "isTemplate": false,
    "count": 1
  },
  {
    "id": "36b2f2f3-3ab6-439c-a127-8320a1e4c168",
    "data": [
      {
        "text": "akun toko cash tidak bsa diaktifkan menjadi ovo",
        "userDefined": false
      }
    ],
    "isTemplate": false,
    "count": 1
  },
  {
    "id": "4544ef02-fd88-4117-841b-9761dc5b4985",
    "data": [
      {
        "text": "tidak bs aktivasi ovo cash",
        "userDefined": false
      }
    ],
    "isTemplate": false,
    "count": 1
  },
  {
    "id": "343fc9cf-2fde-414e-9e32-3e3aeaeebe0d",
    "data": [
      {
        "text": "aktifasi ovo gagal, padahal saya sudah download ovo dan sudah punya akun ny (daftar via ovo)",
        "userDefined": false
      }
    ],
    "isTemplate": false,
    "count": 1
  },
  {
    "id": "b907b536-afd9-464b-990b-b0c9ba536227",
    "data": [
      {
        "text": "belum terverifikasi kode (OTP) yang dikirimkan melalui SMS tidak bisa dimasukan",
        "userDefined": false
      }
    ],
    "isTemplate": false,
    "count": 1
  },
  {
    "id": "0c831eb2-4f72-458b-b8c7-1f55b4cc41cf",
    "data": [
      {
        "text": "Saya sudah aktifkan ovo di no hp saya tetapi kenapa tidak tersambung dengan ovo di tokopedia",
        "userDefined": false
      }
    ],
    "isTemplate": false,
    "count": 1
  },
  {
    "id": "11bedd09-31a6-40a8-9360-5124bb1c65e0",
    "data": [
      {
        "text": "sy ada dana tokocash tp tidak bisa aktivasi OVO, sebagai informasi sy punya OVO di aplikasi Grab di nomor HP yang sama dgn tokopedia",
        "userDefined": false
      }
    ],
    "isTemplate": false,
    "count": 1
  },
  {
    "id": "f6b5ac51-a540-4ee8-a563-fc3255d0da4a",
    "data": [
      {
        "text": "kenapa ya ovo saya tidak connect di akun saya.tulisannya gagal.dan tidak bisa di coba lagi",
        "userDefined": false
      }
    ],
    "isTemplate": false,
    "count": 1
  },
  {
    "id": "6665ded9-d2ae-4e57-82a0-6f35818a2c9f",
    "data": [
      {
        "text": "sy ingin bertanya knp dr kmrn sy coba aktifasi OVO sy tp tdk bisa trs y?",
        "userDefined": false
      }
    ],
    "isTemplate": false,
    "count": 1
  },
  {
    "id": "b1da9459-ec02-4526-9d3f-ad2498595ece",
    "data": [
      {
        "text": "ovo ga bisa aktivasi padahal kode sudah benar",
        "userDefined": false
      }
    ],
    "isTemplate": false,
    "count": 1
  },
  {
    "id": "681b8ae8-b9ea-4b61-8e1e-ba196a50c280",
    "data": [
      {
        "text": "tidak bisa verifikasi kode ovo",
        "userDefined": false
      }
    ],
    "isTemplate": false,
    "count": 1
  },
  {
    "id": "96cd5df4-3e69-49b1-88f3-440109a92095",
    "data": [
      {
        "text": "tdk bisa aktivasi ovo ngga dpt kode verifikasi",
        "userDefined": false
      }
    ],
    "isTemplate": false,
    "count": 1
  },
  {
    "id": "ad18035a-8c57-4777-b02e-4e76be2d6a85",
    "data": [
      {
        "text": "pada saat membayar dg OVO cash saya diminta security code tapi saya tidak menerima kode OTP melalui sms",
        "userDefined": false
      }
    ],
    "isTemplate": false,
    "count": 1
  },
  {
    "id": "55993833-822a-4caa-aa9c-95db75c416d9",
    "data": [
      {
        "text": "kode verifikasi ovo saya tidak bisa",
        "userDefined": false
      }
    ],
    "isTemplate": false,
    "count": 1
  },
  {
    "id": "7f57543f-4e9e-4d76-89b5-d8e819749461",
    "data": [
      {
        "text": "bisa tanya tentang aktivasi OVO, kenapa selalu tidak berhasil dengan pop up: salah kode OTP.",
        "userDefined": false
      }
    ],
    "isTemplate": false,
    "count": 1
  },
  {
    "id": "a549ca5c-010d-4b68-9b6f-1e31a7a0bfd6",
    "data": [
      {
        "text": "Kenapa setiap saya memasukkan kode verifikasi utk aktifkan OVO sll gagal?",
        "userDefined": false
      }
    ],
    "isTemplate": false,
    "count": 1
  },
  {
    "id": "53bd4d13-ecfa-466b-9f8e-5eaf30ed3f14",
    "data": [
      {
        "text": "min mau taya...tolong di bantu dong...saya mau aktifin ovo ko ga bisa yah.",
        "userDefined": false
      }
    ],
    "isTemplate": false,
    "count": 1
  },
  {
    "id": "8a69c98e-7235-4dd0-bb1e-16d6f41bd890",
    "data": [
      {
        "text": "saya dapat email bahwa tokocash berubah jadi ovo tapi saat saya mau aktifkan tidak ada fitur itu di apps. saya sudah update aplikasinya",
        "userDefined": false
      }
    ],
    "isTemplate": false,
    "count": 1
  },
  {
    "id": "0f92db8c-1a69-4978-8f67-16bfec5d17db",
    "data": [
      {
        "text": "Saya ingin tanya bagaimana menyatukan tokocash saya dengan OVO.",
        "userDefined": false
      }
    ],
    "isTemplate": false,
    "count": 1
  },
  {
    "id": "8f600303-61be-40df-95d5-ab74aace698a",
    "data": [
      {
        "text": "masih belum bisa.mengaktifkan/aktivasi ovo",
        "userDefined": false
      }
    ],
    "isTemplate": false,
    "count": 1
  },
  {
    "id": "7e42819c-4bb6-4ae9-b32d-469f91c87049",
    "data": [
      {
        "text": "Gagal aktifasi OVO",
        "userDefined": false
      }
    ],
    "isTemplate": false,
    "count": 1
  },
  {
    "id": "58756a5f-2f8c-452f-85cf-0e43af30c937",
    "data": [
      {
        "text": "tdk bisa konfirmasi kode ovo",
        "userDefined": false
      }
    ],
    "isTemplate": false,
    "count": 1
  },
  {
    "id": "00a86d28-8baa-47f0-b2b1-1b4558669695",
    "data": [
      {
        "text": "aplikasi tokopedia tidak bisa terhubung dengan OVO nomor hp sudah benar",
        "userDefined": false
      }
    ],
    "isTemplate": false,
    "count": 1
  },
  {
    "id": "a834a267-58e6-40b2-9799-a0e696927eb8",
    "data": [
      {
        "text": "sy mau mengaktivasi tokocash ovo....? kok td bs yaa",
        "userDefined": false
      }
    ],
    "isTemplate": false,
    "count": 1
  },
  {
    "id": "5ad276d9-e50c-4d77-aacb-c58637450494",
    "data": [
      {
        "text": "migrasi dari saldo toko cash ke ovo. setelah saya ikuti langkah2 nya. knapa terhenti di ulangi kode sekali lg tidak ada tombol next nya. mohon bntuannya.trims",
        "userDefined": false
      }
    ],
    "isTemplate": false,
    "count": 1
  },
  {
    "id": "18709e02-06d1-495a-b16a-843351fa7ad9",
    "data": [
      {
        "text": "kenapa tidak ada pilihan (opsi) untuk akun saya supaya bisa terhubung dengan OVO ... padahal teman2 saya dibagian homepage tokopedia ada pilihan untuk aktivasi ke OVO",
        "userDefined": false
      }
    ],
    "isTemplate": false,
    "count": 1
  },
  {
    "id": "ae8a8d29-17cb-40ca-959e-00c0c27fc22f",
    "data": [
      {
        "text": "saya ingin bertanya seputar ovocash sedangkan ke5 akun tersebut terdaftar dengan nomor hp yang berbeda",
        "userDefined": false
      }
    ],
    "isTemplate": false,
    "count": 1
  },
  {
    "id": "4393221e-a7d2-490e-80fe-c6e0ed0fae93",
    "data": [
      {
        "text": "Belum bisa connect ke ovo.",
        "userDefined": false
      }
    ],
    "isTemplate": false,
    "count": 1
  },
  {
    "id": "f4dcf2d4-2c73-443e-be29-09cd728d4c8b",
    "data": [
      {
        "text": "halo saya tidak bisa mengaktifkan ovo saya.",
        "userDefined": false
      }
    ],
    "isTemplate": false,
    "count": 1
  },
  {
    "id": "a5ce9d2a-4945-45cf-abe4-fbba181a4c09",
    "data": [
      {
        "text": "tidak bisa aktivasi ovo",
        "userDefined": false
      }
    ],
    "isTemplate": false,
    "count": 1
  },
  {
    "id": "a7ea7c81-5967-4b92-8949-dc3123abd340",
    "data": [
      {
        "text": "sy tidak berhasil melakukan aktivasi ovo.",
        "userDefined": false
      }
    ],
    "isTemplate": false,
    "count": 1
  }
]