[
  {
    "id": "e765f984-8302-4f16-8500-d5cbb625c9b7",
    "data": [
      {
        "text": "saya sudah melakukan transaksi",
        "userDefined": false
      }
    ],
    "isTemplate": false,
    "count": 1
  },
  {
    "id": "fe29534a-8eb4-4e41-9127-9b6df1255bee",
    "data": [
      {
        "text": "cudah",
        "userDefined": false
      }
    ],
    "isTemplate": false,
    "count": 0
  },
  {
    "id": "3d0b9034-1e96-42cf-a68e-5cc7a7ceaba5",
    "data": [
      {
        "text": "sdh",
        "userDefined": false
      }
    ],
    "isTemplate": false,
    "count": 0
  },
  {
    "id": "7892e04f-9c0e-4d86-87ea-27d5d06b18f8",
    "data": [
      {
        "text": "sudah transaksi",
        "userDefined": false
      }
    ],
    "isTemplate": false,
    "count": 0
  },
  {
    "id": "17ff0feb-6a2e-403d-a86b-2bd0051b30a0",
    "data": [
      {
        "text": "sudah",
        "userDefined": false
      }
    ],
    "isTemplate": false,
    "count": 0
  },
  {
    "id": "c6f178a0-43cd-40d8-9cb5-8bc0fdc04a36",
    "data": [
      {
        "text": "sudah melakukan transaksi",
        "userDefined": false
      }
    ],
    "isTemplate": false,
    "count": 0
  },
  {
    "id": "b7da7668-0d85-4b4b-ba17-67f27a2d8ba9",
    "data": [
      {
        "text": "sudah kak",
        "userDefined": false
      }
    ],
    "isTemplate": false,
    "count": 0
  },
  {
    "id": "e7c008c7-acb3-4c41-8ddb-6cdd5104e4eb",
    "data": [
      {
        "text": "udah",
        "userDefined": false
      }
    ],
    "isTemplate": false,
    "count": 0
  },
  {
    "id": "f562cfa5-cb76-45e7-9712-8b8c7b46ec31",
    "data": [
      {
        "text": "syudah",
        "userDefined": false
      }
    ],
    "isTemplate": false,
    "count": 0
  },
  {
    "id": "840b2d12-ac95-45ae-988b-8aabb7a175b8",
    "data": [
      {
        "text": "sudah bertransaksi",
        "userDefined": false
      }
    ],
    "isTemplate": false,
    "count": 0
  },
  {
    "id": "55a3fd98-5d74-4cfe-ab15-07c21fbccaf4",
    "data": [
      {
        "text": "udh",
        "userDefined": false
      }
    ],
    "isTemplate": false,
    "count": 0
  },
  {
    "id": "20b72253-df02-4427-9f27-e7f4f0e8ef3c",
    "data": [
      {
        "text": "sudaaaah",
        "userDefined": false
      }
    ],
    "isTemplate": false,
    "count": 0
  }
]