[
  {
    "id": "1bef1e83-5985-4e44-a406-e3e03cdfdbb9",
    "data": [
      {
        "text": "duaaa",
        "userDefined": false
      }
    ],
    "isTemplate": false,
    "count": 0
  },
  {
    "id": "aa9c4e6d-3d98-4008-b448-ec44e7b1b6e3",
    "data": [
      {
        "text": "top up dan tagihan",
        "userDefined": false
      }
    ],
    "isTemplate": false,
    "count": 0
  },
  {
    "id": "40fafeda-546e-4fd0-8b06-e19cecf1bca6",
    "data": [
      {
        "text": "tagihan",
        "userDefined": false
      }
    ],
    "isTemplate": false,
    "count": 0
  },
  {
    "id": "3a64c99e-1701-4781-80df-d7230d74424a",
    "data": [
      {
        "text": "PLN",
        "userDefined": false
      }
    ],
    "isTemplate": false,
    "count": 0
  },
  {
    "id": "8c4b77c0-e5fd-4465-9594-20c80d12af04",
    "data": [
      {
        "text": " Top-Up \u0026 Tagihan",
        "userDefined": false
      }
    ],
    "isTemplate": false,
    "count": 0
  },
  {
    "id": "fe24d38f-5092-4c52-9b36-f7f8fc15231c",
    "data": [
      {
        "text": "2",
        "meta": "@sys.ignore",
        "userDefined": false
      }
    ],
    "isTemplate": false,
    "count": 0
  },
  {
    "id": "d0eef54d-b53e-4976-91b6-e4a30b06394b",
    "data": [
      {
        "text": "produk digital",
        "userDefined": false
      }
    ],
    "isTemplate": false,
    "count": 0
  },
  {
    "id": "38314a62-4ddf-4c9c-9161-30f2d0139052",
    "data": [
      {
        "text": "digi",
        "userDefined": false
      }
    ],
    "isTemplate": false,
    "count": 0
  },
  {
    "id": "2e993a44-4ffb-47da-bed4-8f28e71c6fad",
    "data": [
      {
        "text": "dua",
        "meta": "@sys.ignore",
        "userDefined": false
      }
    ],
    "isTemplate": false,
    "count": 0
  },
  {
    "id": "769681b5-c80b-4c78-998d-d4ace32b7e51",
    "data": [
      {
        "text": "2",
        "meta": "@sys.ignore",
        "userDefined": false
      },
      {
        "text": ".  Top-Up \u0026 Tagihan",
        "userDefined": false
      }
    ],
    "isTemplate": false,
    "count": 0
  },
  {
    "id": "0241f9b8-8b57-4116-855c-2a1e45d09d46",
    "data": [
      {
        "text": "pembelian digital",
        "userDefined": false
      }
    ],
    "isTemplate": false,
    "count": 0
  },
  {
    "id": "7d2eb580-1be9-49f5-b034-537893d50e74",
    "data": [
      {
        "text": "top up",
        "userDefined": false
      }
    ],
    "isTemplate": false,
    "count": 0
  },
  {
    "id": "f421ed0d-75ae-4b4a-aa49-9f61b583d535",
    "data": [
      {
        "text": "pulsa",
        "userDefined": false
      }
    ],
    "isTemplate": false,
    "count": 0
  },
  {
    "id": "e70a6d8a-6130-42e3-a78e-4ffac29a97fd",
    "data": [
      {
        "text": "digital",
        "userDefined": false
      }
    ],
    "isTemplate": false,
    "count": 0
  }
]