[
  {
    "id": "b779e75e-0886-4c95-8509-b0555bc50367",
    "data": [
      {
        "text": "sudah sesuai",
        "userDefined": false
      }
    ],
    "isTemplate": false,
    "count": 0
  },
  {
    "id": "a2a01105-9226-4898-a3f4-ff1f35299377",
    "data": [
      {
        "text": "iya sudah sesuai",
        "userDefined": false
      }
    ],
    "isTemplate": false,
    "count": 0
  },
  {
    "id": "01596c86-e9b6-483e-8b6b-1b84cb95c53f",
    "data": [
      {
        "text": "sesuai",
        "userDefined": false
      }
    ],
    "isTemplate": false,
    "count": 0
  },
  {
    "id": "ae660073-36ea-4eff-94f6-38be82c831e5",
    "data": [
      {
        "text": "udah sama nih",
        "userDefined": false
      }
    ],
    "isTemplate": false,
    "count": 0
  },
  {
    "id": "c738c337-1c2a-4583-a4d7-efef835fccaf",
    "data": [
      {
        "text": "persis",
        "userDefined": false
      }
    ],
    "isTemplate": false,
    "count": 0
  },
  {
    "id": "17fe2589-89da-40d9-b656-abe5553acbd4",
    "data": [
      {
        "text": "iya, sesuai",
        "userDefined": false
      }
    ],
    "isTemplate": false,
    "count": 0
  },
  {
    "id": "b6a86169-cac9-41c1-b349-dd63c31b137f",
    "data": [
      {
        "text": "sama",
        "userDefined": false
      }
    ],
    "isTemplate": false,
    "count": 0
  },
  {
    "id": "1c484eba-2fb4-4275-b85f-7d5c0738377d",
    "data": [
      {
        "text": "udah sesuai nih",
        "userDefined": false
      }
    ],
    "isTemplate": false,
    "count": 0
  },
  {
    "id": "78543016-72d0-4677-b005-cf442a2fba75",
    "data": [
      {
        "text": "sesuai ya",
        "userDefined": false
      }
    ],
    "isTemplate": false,
    "count": 0
  },
  {
    "id": "7166f5ef-90f2-4f7d-82b2-e3cae6797fa3",
    "data": [
      {
        "text": "memang sesuai",
        "userDefined": false
      }
    ],
    "isTemplate": false,
    "count": 0
  },
  {
    "id": "777af4d4-6a76-4a2b-be1b-6ce084d8cf17",
    "data": [
      {
        "text": "sudah sesuai dengan ini",
        "userDefined": false
      }
    ],
    "isTemplate": false,
    "count": 0
  },
  {
    "id": "43aa3fc5-a356-41b7-9b71-a9fd1b5cd5a7",
    "data": [
      {
        "text": "sesuai kok",
        "userDefined": false
      }
    ],
    "isTemplate": false,
    "count": 0
  },
  {
    "id": "67e1d0eb-c050-435f-a187-62a788b505cc",
    "data": [
      {
        "text": "udah sesuai",
        "userDefined": false
      }
    ],
    "isTemplate": false,
    "count": 0
  }
]